aineko_plugins/nodes/websocket_client/__init__.py
aineko_plugins/nodes/websocket_client/py.typed
aineko_plugins/nodes/websocket_client/websocket_client.py
aineko_plugins_nodes_websocket_client-0.0.3.dist-info/LICENSE
aineko_plugins_nodes_websocket_client-0.0.3.dist-info/METADATA
aineko_plugins_nodes_websocket_client-0.0.3.dist-info/WHEEL
aineko_plugins_nodes_websocket_client-0.0.3.dist-info/RECORD
